zetamarkets/__init__.py
zetamarkets-0.0.1a0.dist-info/WHEEL
zetamarkets-0.0.1a0.dist-info/METADATA
zetamarkets-0.0.1a0.dist-info/RECORD
