Metadata-Version: 2.1
Name: zetamarkets
Version: 0.0.1a0
Summary: Coming on Saturday
License: MIT
Author: Joel Lee
Author-email: joel@joellee.org
Requires-Python: >=3.7,<4.0
Classifier: License :: OSI Approved :: MIT License
Classifier: Programming Language :: Python :: 3
Classifier: Programming Language :: Python :: 3.10
Classifier: Programming Language :: Python :: 3.7
Classifier: Programming Language :: Python :: 3.8
Classifier: Programming Language :: Python :: 3.9
